physbeh/__init__.py
physbeh/conftest.py
physbeh/arena/__init__.py
physbeh/arena/base.py
physbeh/arena/rectangle.py
physbeh/io/__init__.py
physbeh/io/files.py
physbeh/plotting/__init__.py
physbeh/plotting/animate2d_decorator.py
physbeh/plotting/animate_decorator.py
physbeh/plotting/figure.py
physbeh/plotting/plotting.py
physbeh/tracking/__init__.py
physbeh/tracking/tracking.py
physbeh/utils/__init__.py
physbeh/utils/parallel.py
physbeh/utils/place_fields.py
physbeh/utils/utils.py
physbeh-0.6.6.dist-info/METADATA
physbeh-0.6.6.dist-info/WHEEL
physbeh-0.6.6.dist-info/licenses/LICENSE
physbeh-0.6.6.dist-info/RECORD
