Metadata-Version: 2.4
Name: physbeh
Version: 0.6.6
Summary: Miscellaneous functions for tracking analysis in Python using DeepLabCut at Physics for Medicine
Project-URL: repository, https://github.com/FelipeCybis/physbeh
Author-email: Felipe Cybis Pereira <felipe.cybispereira@gmail.com>
License: Copyright 2026 Felipe Cybis Pereira
License-File: LICENSE
Classifier: License :: OSI Approved :: MIT License
Classifier: Programming Language :: Python
Classifier: Programming Language :: Python :: 3
Requires-Python: <3.14,>=3.10
Requires-Dist: joblib~=1.5.0
Requires-Dist: matplotlib~=3.10
Requires-Dist: numpy<3,>=1.24
Requires-Dist: opencv-python>=4.10.0.84
Requires-Dist: pandas[pyarrow]~=2.2
Requires-Dist: pint-pandas~=0.5
Requires-Dist: ruamel-yaml~=0.19.0
Requires-Dist: scipy~=1.12
Requires-Dist: tables~=3.10
Requires-Dist: tqdm~=4.66
Provides-Extra: all
Requires-Dist: numpydoc~=1.10.0; extra == 'all'
Requires-Dist: pre-commit; extra == 'all'
Requires-Dist: pydata-sphinx-theme~=0.14; extra == 'all'
Requires-Dist: pytest-cov>=6.0.0; extra == 'all'
Requires-Dist: pytest~=9.0.2; extra == 'all'
Requires-Dist: sphinx-copybutton~=0.5; extra == 'all'
Requires-Dist: sphinx-design~=0.5; extra == 'all'
Requires-Dist: sphinx-gallery>=0.18.0; extra == 'all'
Requires-Dist: sphinx~=8.0; extra == 'all'
Provides-Extra: dev
Requires-Dist: pre-commit; extra == 'dev'
Provides-Extra: docs
Requires-Dist: numpydoc~=1.10.0; extra == 'docs'
Requires-Dist: pydata-sphinx-theme~=0.14; extra == 'docs'
Requires-Dist: sphinx-copybutton~=0.5; extra == 'docs'
Requires-Dist: sphinx-design~=0.5; extra == 'docs'
Requires-Dist: sphinx-gallery>=0.18.0; extra == 'docs'
Requires-Dist: sphinx~=8.0; extra == 'docs'
Provides-Extra: test
Requires-Dist: pytest-cov>=6.0.0; extra == 'test'
Requires-Dist: pytest~=9.0.2; extra == 'test'
